aiworkflows/__init__.py
aiworkflows/cli.py
aiworkflows/api/__init__.py
aiworkflows/api/api.py
aiworkflows/api/tasks.py
aiworkflows/api/utils/__init__.py
aiworkflows/api/utils/request_handler.py
aiworkflows/compiler/__init__.py
aiworkflows/compiler/task_compiler.py
aiworkflows/compiler/utils/__init__.py
aiworkflows/compiler/utils/json_utils.py
aiworkflows/models/__init__.py
aiworkflows/models/ai_model_source.py
aiworkflows/models/ai_task.py
aiworkflows/models/ai_task_call.py
aiworkflows/models/ai_task_call_usage.py
aiworkflows/models/ai_task_configuration.py
aiworkflows/models/ai_task_data_object.py
aiworkflows/models/ai_task_error_options.py
aiworkflows/models/ai_task_execution.py
aiworkflows/models/ai_task_input.py
aiworkflows/models/ai_task_output.py
aiworkflows/models/ai_task_primitive_type.py
aiworkflows-0.0.4.dist-info/METADATA
aiworkflows-0.0.4.dist-info/WHEEL
aiworkflows-0.0.4.dist-info/entry_points.txt
aiworkflows-0.0.4.dist-info/top_level.txt
aiworkflows-0.0.4.dist-info/RECORD
