Metadata-Version: 2.1
Name: aiworkflows
Version: 0.0.4
Summary: AI Workflows Python SDK
Home-page: https://github.com/ai-workflows/sdk
Author: Joseph Vitko
Author-email: me@josephvitko.com
License: MIT
Classifier: Development Status :: 1 - Planning
Requires-Python: >=3.10
Requires-Dist: requests
Requires-Dist: python-dotenv
